[{"text":"앵커 생계 보조나 사회적 배려라는 인식이 강했던 노인형 일자리 사업이","start":6.099,"duration":2.525},{"text":"진화하고 있습니다","start":8.657,"duration":2.34},{"text":"어르신들의 성취감을 높이면서 쏠쏠한 이익까지 내서 상여까지 지급하는 수익형","start":11.03,"duration":3.001},{"text":"일자리가 늘고 있다고 합니다","start":14.064,"duration":3.895},{"text":"박상규 기자입니다","start":17.992,"duration":3.839},{"text":"기자 고객을 맞이하고 상품을 진열하고 재고 관리도 능숙합니다","start":21.864,"duration":6.984},{"text":"어르신들의 손길이 분주한 이곳은 경기도고양시가 기획한 시니어 동행","start":28.881,"duration":1.918},{"text":"편의점입니다","start":30.832,"duration":6.951},{"text":"한 번에 6시간씩 한 주 2번 열네 분이 교대로 근무합니다","start":37.816,"duration":2.9},{"text":"최저임금 대비 10 이상 높은 급여를 받고 운영 수익이 나면 상여금도 받을 수 있어","start":40.749,"duration":9.189},{"text":"활기가 넘칩니다","start":49.971,"duration":2.167},{"text":"기자 재단과 박음질 작업이 한창인 이곳은 과거 양장점 수선집 등에서 솜씨를","start":52.171,"duration":8.842},{"text":"뽐냈던 할머니들의 새 일터입니다","start":61.046,"duration":3.786},{"text":"신생아 의류와 장난감 등 각종 봉제 상품을만드는데 추가 고용이 필요할 정도로","start":64.865,"duration":9.013},{"text":"일감이 밀려들고 있습니다","start":73.911,"duration":4.153},{"text":"기자 철저한 위생 관리로 HACCP 인증까지 받은 참기름 들기름을 생산하는","start":78.097,"duration":10.009},{"text":"어르신들도 있습니다","start":88.139,"duration":2.334},{"text":"주문 당일 생산 납품 원칙을 고집하면서 로컬 푸드 매장 인기 상품에 이름을","start":90.506,"duration":7.503},{"text":"올렸습니다","start":98.042,"duration":4.198},{"text":"기자 우리나라의 65세 이상 고령 인구는약 200만 명","start":102.273,"duration":9.148},{"text":"사회적 배려를 넘어 만족도와 지속가능성을 모두 높일 수 있는 노인 일자리","start":111.454,"duration":3.779},{"text":"발굴로 내실을 다져야 할 시점입니다","start":115.266,"duration":2.899},{"text":"MBC 뉴스 박상규입니다","start":118.198,"duration":4.835}]